// class version 46.0 (46)
// access flags 0x1
public class net/sf/cglib/proxy/Enhancer$EnhancerKey$$KeyFactoryByCGLIB$$7fb24d72 extends net/sf/cglib/core/KeyFactory  implements net/sf/cglib/proxy/Enhancer$EnhancerKey  {

  // compiled from: <generated>

  // access flags 0x12
  private final Ljava/lang/String; FIELD_0

  // access flags 0x12
  private final [Ljava/lang/String; FIELD_1

  // access flags 0x12
  private final Lnet/sf/cglib/core/WeakCacheKey; FIELD_2

  // access flags 0x12
  private final [Lorg/objectweb/asm/Type; FIELD_3

  // access flags 0x12
  private final Z FIELD_4

  // access flags 0x12
  private final Z FIELD_5

  // access flags 0x12
  private final Ljava/lang/Long; FIELD_6

  // access flags 0x1
  public <init>()V
    ALOAD 0
    INVOKESPECIAL net/sf/cglib/core/KeyFactory.<init> ()V
    RETURN
    MAXSTACK = 1
    MAXLOCALS = 1

  // access flags 0x1
  public newInstance(Ljava/lang/String;[Ljava/lang/String;Lnet/sf/cglib/core/WeakCacheKey;[Lorg/objectweb/asm/Type;ZZLjava/lang/Long;)Ljava/lang/Object;
    NEW net/sf/cglib/proxy/Enhancer$EnhancerKey$$KeyFactoryByCGLIB$$7fb24d72
    DUP
    ALOAD 1
    ALOAD 2
    ALOAD 3
    ALOAD 4
    ILOAD 5
    ILOAD 6
    ALOAD 7
    INVOKESPECIAL net/sf/cglib/proxy/Enhancer$EnhancerKey$$KeyFactoryByCGLIB$$7fb24d72.<init> (Ljava/lang/String;[Ljava/lang/String;Lnet/sf/cglib/core/WeakCacheKey;[Lorg/objectweb/asm/Type;ZZLjava/lang/Long;)V
    ARETURN
    MAXSTACK = 9
    MAXLOCALS = 8

  // access flags 0x1
  public <init>(Ljava/lang/String;[Ljava/lang/String;Lnet/sf/cglib/core/WeakCacheKey;[Lorg/objectweb/asm/Type;ZZLjava/lang/Long;)V
    ALOAD 0
    INVOKESPECIAL net/sf/cglib/core/KeyFactory.<init> ()V
    ALOAD 0
    DUP
    ALOAD 1
    PUTFIELD net/sf/cglib/proxy/Enhancer$EnhancerKey$$KeyFactoryByCGLIB$$7fb24d72.FIELD_0 : Ljava/lang/String;
    DUP
    ALOAD 2
    PUTFIELD net/sf/cglib/proxy/Enhancer$EnhancerKey$$KeyFactoryByCGLIB$$7fb24d72.FIELD_1 : [Ljava/lang/String;
    DUP
    ALOAD 3
    PUTFIELD net/sf/cglib/proxy/Enhancer$EnhancerKey$$KeyFactoryByCGLIB$$7fb24d72.FIELD_2 : Lnet/sf/cglib/core/WeakCacheKey;
    DUP
    ALOAD 4
    PUTFIELD net/sf/cglib/proxy/Enhancer$EnhancerKey$$KeyFactoryByCGLIB$$7fb24d72.FIELD_3 : [Lorg/objectweb/asm/Type;
    DUP
    ILOAD 5
    PUTFIELD net/sf/cglib/proxy/Enhancer$EnhancerKey$$KeyFactoryByCGLIB$$7fb24d72.FIELD_4 : Z
    DUP
    ILOAD 6
    PUTFIELD net/sf/cglib/proxy/Enhancer$EnhancerKey$$KeyFactoryByCGLIB$$7fb24d72.FIELD_5 : Z
    DUP
    ALOAD 7
    PUTFIELD net/sf/cglib/proxy/Enhancer$EnhancerKey$$KeyFactoryByCGLIB$$7fb24d72.FIELD_6 : Ljava/lang/Long;
    RETURN
    MAXSTACK = 3
    MAXLOCALS = 8

  // access flags 0x1
  public hashCode()I
    SIPUSH 19289
    ALOAD 0
    GETFIELD net/sf/cglib/proxy/Enhancer$EnhancerKey$$KeyFactoryByCGLIB$$7fb24d72.FIELD_0 : Ljava/lang/String;
    SWAP
    LDC 641371
    IMUL
    SWAP
    DUP
    IFNULL L0
    INVOKEVIRTUAL java/lang/Object.hashCode ()I
    GOTO L1
   L0
   FRAME FULL [net/sf/cglib/proxy/Enhancer$EnhancerKey$$KeyFactoryByCGLIB$$7fb24d72] [I java/lang/String]
    POP
    ICONST_0
   L1
   FRAME FULL [net/sf/cglib/proxy/Enhancer$EnhancerKey$$KeyFactoryByCGLIB$$7fb24d72] [I I]
    IADD
    ALOAD 0
    GETFIELD net/sf/cglib/proxy/Enhancer$EnhancerKey$$KeyFactoryByCGLIB$$7fb24d72.FIELD_1 : [Ljava/lang/String;
    DUP
    IFNULL L2
    ASTORE 1
    ICONST_0
    ISTORE 2
    GOTO L3
   L4
   FRAME FULL [net/sf/cglib/proxy/Enhancer$EnhancerKey$$KeyFactoryByCGLIB$$7fb24d72 [Ljava/lang/String; I] [I]
    ALOAD 1
    ILOAD 2
    AALOAD
    SWAP
    LDC 641371
    IMUL
    SWAP
    DUP
    IFNULL L5
    INVOKEVIRTUAL java/lang/Object.hashCode ()I
    GOTO L6
   L5
   FRAME FULL [net/sf/cglib/proxy/Enhancer$EnhancerKey$$KeyFactoryByCGLIB$$7fb24d72 [Ljava/lang/String; I] [I java/lang/String]
    POP
    ICONST_0
   L6
   FRAME FULL [net/sf/cglib/proxy/Enhancer$EnhancerKey$$KeyFactoryByCGLIB$$7fb24d72 [Ljava/lang/String; I] [I I]
    IADD
    IINC 2 1
   L3
   FRAME FULL [net/sf/cglib/proxy/Enhancer$EnhancerKey$$KeyFactoryByCGLIB$$7fb24d72 [Ljava/lang/String; I] [I]
    ILOAD 2
    ALOAD 1
    ARRAYLENGTH
    IF_ICMPLT L4
    GOTO L7
   L2
   FRAME FULL [net/sf/cglib/proxy/Enhancer$EnhancerKey$$KeyFactoryByCGLIB$$7fb24d72] [I [Ljava/lang/String;]
    POP
   L7
   FRAME FULL [net/sf/cglib/proxy/Enhancer$EnhancerKey$$KeyFactoryByCGLIB$$7fb24d72] [I]
    ALOAD 0
    GETFIELD net/sf/cglib/proxy/Enhancer$EnhancerKey$$KeyFactoryByCGLIB$$7fb24d72.FIELD_2 : Lnet/sf/cglib/core/WeakCacheKey;
    SWAP
    LDC 641371
    IMUL
    SWAP
    DUP
    IFNULL L8
    INVOKEVIRTUAL java/lang/Object.hashCode ()I
    GOTO L9
   L8
   FRAME FULL [net/sf/cglib/proxy/Enhancer$EnhancerKey$$KeyFactoryByCGLIB$$7fb24d72] [I net/sf/cglib/core/WeakCacheKey]
    POP
    ICONST_0
   L9
   FRAME FULL [net/sf/cglib/proxy/Enhancer$EnhancerKey$$KeyFactoryByCGLIB$$7fb24d72] [I I]
    IADD
    ALOAD 0
    GETFIELD net/sf/cglib/proxy/Enhancer$EnhancerKey$$KeyFactoryByCGLIB$$7fb24d72.FIELD_3 : [Lorg/objectweb/asm/Type;
    DUP
    IFNULL L10
    ASTORE 3
    ICONST_0
    ISTORE 4
    GOTO L11
   L12
   FRAME FULL [net/sf/cglib/proxy/Enhancer$EnhancerKey$$KeyFactoryByCGLIB$$7fb24d72 T T [Lorg/objectweb/asm/Type; I] [I]
    ALOAD 3
    ILOAD 4
    AALOAD
    SWAP
    LDC 641371
    IMUL
    SWAP
    DUP
    IFNULL L13
    INVOKEVIRTUAL java/lang/Object.hashCode ()I
    GOTO L14
   L13
   FRAME FULL [net/sf/cglib/proxy/Enhancer$EnhancerKey$$KeyFactoryByCGLIB$$7fb24d72 T T [Lorg/objectweb/asm/Type; I] [I org/objectweb/asm/Type]
    POP
    ICONST_0
   L14
   FRAME FULL [net/sf/cglib/proxy/Enhancer$EnhancerKey$$KeyFactoryByCGLIB$$7fb24d72 T T [Lorg/objectweb/asm/Type; I] [I I]
    IADD
    IINC 4 1
   L11
   FRAME FULL [net/sf/cglib/proxy/Enhancer$EnhancerKey$$KeyFactoryByCGLIB$$7fb24d72 T T [Lorg/objectweb/asm/Type; I] [I]
    ILOAD 4
    ALOAD 3
    ARRAYLENGTH
    IF_ICMPLT L12
    GOTO L15
   L10
   FRAME FULL [net/sf/cglib/proxy/Enhancer$EnhancerKey$$KeyFactoryByCGLIB$$7fb24d72] [I [Lorg/objectweb/asm/Type;]
    POP
   L15
   FRAME FULL [net/sf/cglib/proxy/Enhancer$EnhancerKey$$KeyFactoryByCGLIB$$7fb24d72] [I]
    ALOAD 0
    GETFIELD net/sf/cglib/proxy/Enhancer$EnhancerKey$$KeyFactoryByCGLIB$$7fb24d72.FIELD_4 : Z
    SWAP
    LDC 641371
    IMUL
    SWAP
    ICONST_1
    IXOR
    IADD
    ALOAD 0
    GETFIELD net/sf/cglib/proxy/Enhancer$EnhancerKey$$KeyFactoryByCGLIB$$7fb24d72.FIELD_5 : Z
    SWAP
    LDC 641371
    IMUL
    SWAP
    ICONST_1
    IXOR
    IADD
    ALOAD 0
    GETFIELD net/sf/cglib/proxy/Enhancer$EnhancerKey$$KeyFactoryByCGLIB$$7fb24d72.FIELD_6 : Ljava/lang/Long;
    SWAP
    LDC 641371
    IMUL
    SWAP
    DUP
    IFNULL L16
    INVOKEVIRTUAL java/lang/Object.hashCode ()I
    GOTO L17
   L16
   FRAME FULL [net/sf/cglib/proxy/Enhancer$EnhancerKey$$KeyFactoryByCGLIB$$7fb24d72] [I java/lang/Long]
    POP
    ICONST_0
   L17
   FRAME FULL [net/sf/cglib/proxy/Enhancer$EnhancerKey$$KeyFactoryByCGLIB$$7fb24d72] [I I]
    IADD
    IRETURN
    MAXSTACK = 3
    MAXLOCALS = 5

  // access flags 0x1
  public equals(Ljava/lang/Object;)Z
    ALOAD 1
    INSTANCEOF net/sf/cglib/proxy/Enhancer$EnhancerKey$$KeyFactoryByCGLIB$$7fb24d72
    IFEQ L0
    ALOAD 0
    GETFIELD net/sf/cglib/proxy/Enhancer$EnhancerKey$$KeyFactoryByCGLIB$$7fb24d72.FIELD_0 : Ljava/lang/String;
    ALOAD 1
    CHECKCAST net/sf/cglib/proxy/Enhancer$EnhancerKey$$KeyFactoryByCGLIB$$7fb24d72
    GETFIELD net/sf/cglib/proxy/Enhancer$EnhancerKey$$KeyFactoryByCGLIB$$7fb24d72.FIELD_0 : Ljava/lang/String;
    DUP2
    IFNONNULL L1
    IFNONNULL L2
    POP2
    GOTO L3
   L1
   FRAME FULL [net/sf/cglib/proxy/Enhancer$EnhancerKey$$KeyFactoryByCGLIB$$7fb24d72 java/lang/Object] [java/lang/String java/lang/String java/lang/String]
    IFNULL L2
    GOTO L4
   L2
   FRAME FULL [net/sf/cglib/proxy/Enhancer$EnhancerKey$$KeyFactoryByCGLIB$$7fb24d72 java/lang/Object] [java/lang/String java/lang/String]
    POP2
    GOTO L0
   L4
   FRAME FULL [net/sf/cglib/proxy/Enhancer$EnhancerKey$$KeyFactoryByCGLIB$$7fb24d72 java/lang/Object] [java/lang/String java/lang/String]
    INVOKEVIRTUAL java/lang/Object.equals (Ljava/lang/Object;)Z
    IFEQ L0
   L3
   FRAME FULL [net/sf/cglib/proxy/Enhancer$EnhancerKey$$KeyFactoryByCGLIB$$7fb24d72 java/lang/Object] []
    ALOAD 0
    GETFIELD net/sf/cglib/proxy/Enhancer$EnhancerKey$$KeyFactoryByCGLIB$$7fb24d72.FIELD_1 : [Ljava/lang/String;
    ALOAD 1
    CHECKCAST net/sf/cglib/proxy/Enhancer$EnhancerKey$$KeyFactoryByCGLIB$$7fb24d72
    GETFIELD net/sf/cglib/proxy/Enhancer$EnhancerKey$$KeyFactoryByCGLIB$$7fb24d72.FIELD_1 : [Ljava/lang/String;
    DUP2
    IFNONNULL L5
    IFNONNULL L6
    POP2
    GOTO L7
   L5
   FRAME FULL [net/sf/cglib/proxy/Enhancer$EnhancerKey$$KeyFactoryByCGLIB$$7fb24d72 java/lang/Object] [[Ljava/lang/String; [Ljava/lang/String; [Ljava/lang/String;]
    IFNULL L6
    GOTO L8
   L6
   FRAME FULL [net/sf/cglib/proxy/Enhancer$EnhancerKey$$KeyFactoryByCGLIB$$7fb24d72 java/lang/Object] [[Ljava/lang/String; [Ljava/lang/String;]
    POP2
    GOTO L0
   L8
   FRAME FULL [net/sf/cglib/proxy/Enhancer$EnhancerKey$$KeyFactoryByCGLIB$$7fb24d72 java/lang/Object] [[Ljava/lang/String; [Ljava/lang/String;]
    DUP2
    ARRAYLENGTH
    SWAP
    ARRAYLENGTH
    IF_ICMPEQ L9
    POP2
    GOTO L0
   L9
   FRAME FULL [net/sf/cglib/proxy/Enhancer$EnhancerKey$$KeyFactoryByCGLIB$$7fb24d72 java/lang/Object] [[Ljava/lang/String; [Ljava/lang/String;]
    ASTORE 2
    ASTORE 3
    ICONST_0
    ISTORE 4
    GOTO L10
   L11
   FRAME FULL [net/sf/cglib/proxy/Enhancer$EnhancerKey$$KeyFactoryByCGLIB$$7fb24d72 java/lang/Object [Ljava/lang/String; [Ljava/lang/String; I] []
    ALOAD 2
    ILOAD 4
    AALOAD
    ALOAD 3
    ILOAD 4
    AALOAD
    DUP2
    IFNONNULL L12
    IFNONNULL L13
    POP2
    GOTO L14
   L12
   FRAME FULL [net/sf/cglib/proxy/Enhancer$EnhancerKey$$KeyFactoryByCGLIB$$7fb24d72 java/lang/Object [Ljava/lang/String; [Ljava/lang/String; I] [java/lang/String java/lang/String java/lang/String]
    IFNULL L13
    GOTO L15
   L13
   FRAME FULL [net/sf/cglib/proxy/Enhancer$EnhancerKey$$KeyFactoryByCGLIB$$7fb24d72 java/lang/Object [Ljava/lang/String; [Ljava/lang/String; I] [java/lang/String java/lang/String]
    POP2
    GOTO L0
   L15
   FRAME FULL [net/sf/cglib/proxy/Enhancer$EnhancerKey$$KeyFactoryByCGLIB$$7fb24d72 java/lang/Object [Ljava/lang/String; [Ljava/lang/String; I] [java/lang/String java/lang/String]
    INVOKEVIRTUAL java/lang/Object.equals (Ljava/lang/Object;)Z
    IFEQ L0
   L14
   FRAME FULL [net/sf/cglib/proxy/Enhancer$EnhancerKey$$KeyFactoryByCGLIB$$7fb24d72 java/lang/Object [Ljava/lang/String; [Ljava/lang/String; I] []
    IINC 4 1
   L10
   FRAME FULL [net/sf/cglib/proxy/Enhancer$EnhancerKey$$KeyFactoryByCGLIB$$7fb24d72 java/lang/Object [Ljava/lang/String; [Ljava/lang/String; I] []
    ILOAD 4
    ALOAD 2
    ARRAYLENGTH
    IF_ICMPLT L11
   L7
   FRAME FULL [net/sf/cglib/proxy/Enhancer$EnhancerKey$$KeyFactoryByCGLIB$$7fb24d72 java/lang/Object] []
    ALOAD 0
    GETFIELD net/sf/cglib/proxy/Enhancer$EnhancerKey$$KeyFactoryByCGLIB$$7fb24d72.FIELD_2 : Lnet/sf/cglib/core/WeakCacheKey;
    ALOAD 1
    CHECKCAST net/sf/cglib/proxy/Enhancer$EnhancerKey$$KeyFactoryByCGLIB$$7fb24d72
    GETFIELD net/sf/cglib/proxy/Enhancer$EnhancerKey$$KeyFactoryByCGLIB$$7fb24d72.FIELD_2 : Lnet/sf/cglib/core/WeakCacheKey;
    DUP2
    IFNONNULL L16
    IFNONNULL L17
    POP2
    GOTO L18
   L16
   FRAME FULL [net/sf/cglib/proxy/Enhancer$EnhancerKey$$KeyFactoryByCGLIB$$7fb24d72 java/lang/Object] [net/sf/cglib/core/WeakCacheKey net/sf/cglib/core/WeakCacheKey net/sf/cglib/core/WeakCacheKey]
    IFNULL L17
    GOTO L19
   L17
   FRAME FULL [net/sf/cglib/proxy/Enhancer$EnhancerKey$$KeyFactoryByCGLIB$$7fb24d72 java/lang/Object] [net/sf/cglib/core/WeakCacheKey net/sf/cglib/core/WeakCacheKey]
    POP2
    GOTO L0
   L19
   FRAME FULL [net/sf/cglib/proxy/Enhancer$EnhancerKey$$KeyFactoryByCGLIB$$7fb24d72 java/lang/Object] [net/sf/cglib/core/WeakCacheKey net/sf/cglib/core/WeakCacheKey]
    INVOKEVIRTUAL java/lang/Object.equals (Ljava/lang/Object;)Z
    IFEQ L0
   L18
   FRAME FULL [net/sf/cglib/proxy/Enhancer$EnhancerKey$$KeyFactoryByCGLIB$$7fb24d72 java/lang/Object] []
    ALOAD 0
    GETFIELD net/sf/cglib/proxy/Enhancer$EnhancerKey$$KeyFactoryByCGLIB$$7fb24d72.FIELD_3 : [Lorg/objectweb/asm/Type;
    ALOAD 1
    CHECKCAST net/sf/cglib/proxy/Enhancer$EnhancerKey$$KeyFactoryByCGLIB$$7fb24d72
    GETFIELD net/sf/cglib/proxy/Enhancer$EnhancerKey$$KeyFactoryByCGLIB$$7fb24d72.FIELD_3 : [Lorg/objectweb/asm/Type;
    DUP2
    IFNONNULL L20
    IFNONNULL L21
    POP2
    GOTO L22
   L20
   FRAME FULL [net/sf/cglib/proxy/Enhancer$EnhancerKey$$KeyFactoryByCGLIB$$7fb24d72 java/lang/Object] [[Lorg/objectweb/asm/Type; [Lorg/objectweb/asm/Type; [Lorg/objectweb/asm/Type;]
    IFNULL L21
    GOTO L23
   L21
   FRAME FULL [net/sf/cglib/proxy/Enhancer$EnhancerKey$$KeyFactoryByCGLIB$$7fb24d72 java/lang/Object] [[Lorg/objectweb/asm/Type; [Lorg/objectweb/asm/Type;]
    POP2
    GOTO L0
   L23
   FRAME FULL [net/sf/cglib/proxy/Enhancer$EnhancerKey$$KeyFactoryByCGLIB$$7fb24d72 java/lang/Object] [[Lorg/objectweb/asm/Type; [Lorg/objectweb/asm/Type;]
    DUP2
    ARRAYLENGTH
    SWAP
    ARRAYLENGTH
    IF_ICMPEQ L24
    POP2
    GOTO L0
   L24
   FRAME FULL [net/sf/cglib/proxy/Enhancer$EnhancerKey$$KeyFactoryByCGLIB$$7fb24d72 java/lang/Object] [[Lorg/objectweb/asm/Type; [Lorg/objectweb/asm/Type;]
    ASTORE 5
    ASTORE 6
    ICONST_0
    ISTORE 7
    GOTO L25
   L26
   FRAME FULL [net/sf/cglib/proxy/Enhancer$EnhancerKey$$KeyFactoryByCGLIB$$7fb24d72 java/lang/Object T T T [Lorg/objectweb/asm/Type; [Lorg/objectweb/asm/Type; I] []
    ALOAD 5
    ILOAD 7
    AALOAD
    ALOAD 6
    ILOAD 7
    AALOAD
    DUP2
    IFNONNULL L27
    IFNONNULL L28
    POP2
    GOTO L29
   L27
   FRAME FULL [net/sf/cglib/proxy/Enhancer$EnhancerKey$$KeyFactoryByCGLIB$$7fb24d72 java/lang/Object T T T [Lorg/objectweb/asm/Type; [Lorg/objectweb/asm/Type; I] [org/objectweb/asm/Type org/objectweb/asm/Type org/objectweb/asm/Type]
    IFNULL L28
    GOTO L30
   L28
   FRAME FULL [net/sf/cglib/proxy/Enhancer$EnhancerKey$$KeyFactoryByCGLIB$$7fb24d72 java/lang/Object T T T [Lorg/objectweb/asm/Type; [Lorg/objectweb/asm/Type; I] [org/objectweb/asm/Type org/objectweb/asm/Type]
    POP2
    GOTO L0
   L30
   FRAME FULL [net/sf/cglib/proxy/Enhancer$EnhancerKey$$KeyFactoryByCGLIB$$7fb24d72 java/lang/Object T T T [Lorg/objectweb/asm/Type; [Lorg/objectweb/asm/Type; I] [org/objectweb/asm/Type org/objectweb/asm/Type]
    INVOKEVIRTUAL java/lang/Object.equals (Ljava/lang/Object;)Z
    IFEQ L0
   L29
   FRAME FULL [net/sf/cglib/proxy/Enhancer$EnhancerKey$$KeyFactoryByCGLIB$$7fb24d72 java/lang/Object T T T [Lorg/objectweb/asm/Type; [Lorg/objectweb/asm/Type; I] []
    IINC 7 1
   L25
   FRAME FULL [net/sf/cglib/proxy/Enhancer$EnhancerKey$$KeyFactoryByCGLIB$$7fb24d72 java/lang/Object T T T [Lorg/objectweb/asm/Type; [Lorg/objectweb/asm/Type; I] []
    ILOAD 7
    ALOAD 5
    ARRAYLENGTH
    IF_ICMPLT L26
   L22
   FRAME FULL [net/sf/cglib/proxy/Enhancer$EnhancerKey$$KeyFactoryByCGLIB$$7fb24d72 java/lang/Object] []
    ALOAD 0
    GETFIELD net/sf/cglib/proxy/Enhancer$EnhancerKey$$KeyFactoryByCGLIB$$7fb24d72.FIELD_4 : Z
    ALOAD 1
    CHECKCAST net/sf/cglib/proxy/Enhancer$EnhancerKey$$KeyFactoryByCGLIB$$7fb24d72
    GETFIELD net/sf/cglib/proxy/Enhancer$EnhancerKey$$KeyFactoryByCGLIB$$7fb24d72.FIELD_4 : Z
    IF_ICMPNE L0
    ALOAD 0
    GETFIELD net/sf/cglib/proxy/Enhancer$EnhancerKey$$KeyFactoryByCGLIB$$7fb24d72.FIELD_5 : Z
    ALOAD 1
    CHECKCAST net/sf/cglib/proxy/Enhancer$EnhancerKey$$KeyFactoryByCGLIB$$7fb24d72
    GETFIELD net/sf/cglib/proxy/Enhancer$EnhancerKey$$KeyFactoryByCGLIB$$7fb24d72.FIELD_5 : Z
    IF_ICMPNE L0
    ALOAD 0
    GETFIELD net/sf/cglib/proxy/Enhancer$EnhancerKey$$KeyFactoryByCGLIB$$7fb24d72.FIELD_6 : Ljava/lang/Long;
    ALOAD 1
    CHECKCAST net/sf/cglib/proxy/Enhancer$EnhancerKey$$KeyFactoryByCGLIB$$7fb24d72
    GETFIELD net/sf/cglib/proxy/Enhancer$EnhancerKey$$KeyFactoryByCGLIB$$7fb24d72.FIELD_6 : Ljava/lang/Long;
    DUP2
    IFNONNULL L31
    IFNONNULL L32
    POP2
    GOTO L33
   L31
   FRAME FULL [net/sf/cglib/proxy/Enhancer$EnhancerKey$$KeyFactoryByCGLIB$$7fb24d72 java/lang/Object] [java/lang/Long java/lang/Long java/lang/Long]
    IFNULL L32
    GOTO L34
   L32
   FRAME FULL [net/sf/cglib/proxy/Enhancer$EnhancerKey$$KeyFactoryByCGLIB$$7fb24d72 java/lang/Object] [java/lang/Long java/lang/Long]
    POP2
    GOTO L0
   L34
   FRAME FULL [net/sf/cglib/proxy/Enhancer$EnhancerKey$$KeyFactoryByCGLIB$$7fb24d72 java/lang/Object] [java/lang/Long java/lang/Long]
    INVOKEVIRTUAL java/lang/Object.equals (Ljava/lang/Object;)Z
    IFEQ L0
   L33
   FRAME FULL [net/sf/cglib/proxy/Enhancer$EnhancerKey$$KeyFactoryByCGLIB$$7fb24d72 java/lang/Object] []
    ICONST_1
    IRETURN
   L0
   FRAME FULL [net/sf/cglib/proxy/Enhancer$EnhancerKey$$KeyFactoryByCGLIB$$7fb24d72 java/lang/Object] []
    ICONST_0
    IRETURN
    MAXSTACK = 4
    MAXLOCALS = 8

  // access flags 0x1
  public toString()Ljava/lang/String;
    NEW java/lang/StringBuffer
    DUP
    INVOKESPECIAL java/lang/StringBuffer.<init> ()V
    ALOAD 0
    GETFIELD net/sf/cglib/proxy/Enhancer$EnhancerKey$$KeyFactoryByCGLIB$$7fb24d72.FIELD_0 : Ljava/lang/String;
    DUP
    IFNULL L0
    INVOKEVIRTUAL java/lang/Object.toString ()Ljava/lang/String;
    INVOKEVIRTUAL java/lang/StringBuffer.append (Ljava/lang/String;)Ljava/lang/StringBuffer;
    GOTO L1
   L0
   FRAME FULL [net/sf/cglib/proxy/Enhancer$EnhancerKey$$KeyFactoryByCGLIB$$7fb24d72] [java/lang/StringBuffer java/lang/String]
    POP
    LDC "null"
    INVOKEVIRTUAL java/lang/StringBuffer.append (Ljava/lang/String;)Ljava/lang/StringBuffer;
   L1
   FRAME FULL [net/sf/cglib/proxy/Enhancer$EnhancerKey$$KeyFactoryByCGLIB$$7fb24d72] [java/lang/StringBuffer]
    LDC ", "
    INVOKEVIRTUAL java/lang/StringBuffer.append (Ljava/lang/String;)Ljava/lang/StringBuffer;
    ALOAD 0
    GETFIELD net/sf/cglib/proxy/Enhancer$EnhancerKey$$KeyFactoryByCGLIB$$7fb24d72.FIELD_1 : [Ljava/lang/String;
    DUP
    IFNULL L2
    SWAP
    LDC "{"
    INVOKEVIRTUAL java/lang/StringBuffer.append (Ljava/lang/String;)Ljava/lang/StringBuffer;
    SWAP
    ASTORE 1
    ICONST_0
    ISTORE 2
    GOTO L3
   L4
   FRAME FULL [net/sf/cglib/proxy/Enhancer$EnhancerKey$$KeyFactoryByCGLIB$$7fb24d72 [Ljava/lang/String; I] [java/lang/StringBuffer]
    ALOAD 1
    ILOAD 2
    AALOAD
    DUP
    IFNULL L5
    INVOKEVIRTUAL java/lang/Object.toString ()Ljava/lang/String;
    INVOKEVIRTUAL java/lang/StringBuffer.append (Ljava/lang/String;)Ljava/lang/StringBuffer;
    GOTO L6
   L5
   FRAME FULL [net/sf/cglib/proxy/Enhancer$EnhancerKey$$KeyFactoryByCGLIB$$7fb24d72 [Ljava/lang/String; I] [java/lang/StringBuffer java/lang/String]
    POP
    LDC "null"
    INVOKEVIRTUAL java/lang/StringBuffer.append (Ljava/lang/String;)Ljava/lang/StringBuffer;
   L6
   FRAME FULL [net/sf/cglib/proxy/Enhancer$EnhancerKey$$KeyFactoryByCGLIB$$7fb24d72 [Ljava/lang/String; I] [java/lang/StringBuffer]
    LDC ", "
    INVOKEVIRTUAL java/lang/StringBuffer.append (Ljava/lang/String;)Ljava/lang/StringBuffer;
    IINC 2 1
   L3
   FRAME FULL [net/sf/cglib/proxy/Enhancer$EnhancerKey$$KeyFactoryByCGLIB$$7fb24d72 [Ljava/lang/String; I] [java/lang/StringBuffer]
    ILOAD 2
    ALOAD 1
    ARRAYLENGTH
    IF_ICMPLT L4
    DUP
    DUP
    INVOKEVIRTUAL java/lang/StringBuffer.length ()I
    ICONST_2
    ISUB
    INVOKEVIRTUAL java/lang/StringBuffer.setLength (I)V
    LDC "}"
    INVOKEVIRTUAL java/lang/StringBuffer.append (Ljava/lang/String;)Ljava/lang/StringBuffer;
    GOTO L7
   L2
   FRAME FULL [net/sf/cglib/proxy/Enhancer$EnhancerKey$$KeyFactoryByCGLIB$$7fb24d72] [java/lang/StringBuffer [Ljava/lang/String;]
    POP
    LDC "null"
    INVOKEVIRTUAL java/lang/StringBuffer.append (Ljava/lang/String;)Ljava/lang/StringBuffer;
   L7
   FRAME FULL [net/sf/cglib/proxy/Enhancer$EnhancerKey$$KeyFactoryByCGLIB$$7fb24d72] [java/lang/StringBuffer]
    LDC ", "
    INVOKEVIRTUAL java/lang/StringBuffer.append (Ljava/lang/String;)Ljava/lang/StringBuffer;
    ALOAD 0
    GETFIELD net/sf/cglib/proxy/Enhancer$EnhancerKey$$KeyFactoryByCGLIB$$7fb24d72.FIELD_2 : Lnet/sf/cglib/core/WeakCacheKey;
    DUP
    IFNULL L8
    INVOKEVIRTUAL java/lang/Object.toString ()Ljava/lang/String;
    INVOKEVIRTUAL java/lang/StringBuffer.append (Ljava/lang/String;)Ljava/lang/StringBuffer;
    GOTO L9
   L8
   FRAME FULL [net/sf/cglib/proxy/Enhancer$EnhancerKey$$KeyFactoryByCGLIB$$7fb24d72] [java/lang/StringBuffer net/sf/cglib/core/WeakCacheKey]
    POP
    LDC "null"
    INVOKEVIRTUAL java/lang/StringBuffer.append (Ljava/lang/String;)Ljava/lang/StringBuffer;
   L9
   FRAME FULL [net/sf/cglib/proxy/Enhancer$EnhancerKey$$KeyFactoryByCGLIB$$7fb24d72] [java/lang/StringBuffer]
    LDC ", "
    INVOKEVIRTUAL java/lang/StringBuffer.append (Ljava/lang/String;)Ljava/lang/StringBuffer;
    ALOAD 0
    GETFIELD net/sf/cglib/proxy/Enhancer$EnhancerKey$$KeyFactoryByCGLIB$$7fb24d72.FIELD_3 : [Lorg/objectweb/asm/Type;
    DUP
    IFNULL L10
    SWAP
    LDC "{"
    INVOKEVIRTUAL java/lang/StringBuffer.append (Ljava/lang/String;)Ljava/lang/StringBuffer;
    SWAP
    ASTORE 3
    ICONST_0
    ISTORE 4
    GOTO L11
   L12
   FRAME FULL [net/sf/cglib/proxy/Enhancer$EnhancerKey$$KeyFactoryByCGLIB$$7fb24d72 T T [Lorg/objectweb/asm/Type; I] [java/lang/StringBuffer]
    ALOAD 3
    ILOAD 4
    AALOAD
    DUP
    IFNULL L13
    INVOKEVIRTUAL java/lang/Object.toString ()Ljava/lang/String;
    INVOKEVIRTUAL java/lang/StringBuffer.append (Ljava/lang/String;)Ljava/lang/StringBuffer;
    GOTO L14
   L13
   FRAME FULL [net/sf/cglib/proxy/Enhancer$EnhancerKey$$KeyFactoryByCGLIB$$7fb24d72 T T [Lorg/objectweb/asm/Type; I] [java/lang/StringBuffer org/objectweb/asm/Type]
    POP
    LDC "null"
    INVOKEVIRTUAL java/lang/StringBuffer.append (Ljava/lang/String;)Ljava/lang/StringBuffer;
   L14
   FRAME FULL [net/sf/cglib/proxy/Enhancer$EnhancerKey$$KeyFactoryByCGLIB$$7fb24d72 T T [Lorg/objectweb/asm/Type; I] [java/lang/StringBuffer]
    LDC ", "
    INVOKEVIRTUAL java/lang/StringBuffer.append (Ljava/lang/String;)Ljava/lang/StringBuffer;
    IINC 4 1
   L11
   FRAME FULL [net/sf/cglib/proxy/Enhancer$EnhancerKey$$KeyFactoryByCGLIB$$7fb24d72 T T [Lorg/objectweb/asm/Type; I] [java/lang/StringBuffer]
    ILOAD 4
    ALOAD 3
    ARRAYLENGTH
    IF_ICMPLT L12
    DUP
    DUP
    INVOKEVIRTUAL java/lang/StringBuffer.length ()I
    ICONST_2
    ISUB
    INVOKEVIRTUAL java/lang/StringBuffer.setLength (I)V
    LDC "}"
    INVOKEVIRTUAL java/lang/StringBuffer.append (Ljava/lang/String;)Ljava/lang/StringBuffer;
    GOTO L15
   L10
   FRAME FULL [net/sf/cglib/proxy/Enhancer$EnhancerKey$$KeyFactoryByCGLIB$$7fb24d72] [java/lang/StringBuffer [Lorg/objectweb/asm/Type;]
    POP
    LDC "null"
    INVOKEVIRTUAL java/lang/StringBuffer.append (Ljava/lang/String;)Ljava/lang/StringBuffer;
   L15
   FRAME FULL [net/sf/cglib/proxy/Enhancer$EnhancerKey$$KeyFactoryByCGLIB$$7fb24d72] [java/lang/StringBuffer]
    LDC ", "
    INVOKEVIRTUAL java/lang/StringBuffer.append (Ljava/lang/String;)Ljava/lang/StringBuffer;
    ALOAD 0
    GETFIELD net/sf/cglib/proxy/Enhancer$EnhancerKey$$KeyFactoryByCGLIB$$7fb24d72.FIELD_4 : Z
    INVOKEVIRTUAL java/lang/StringBuffer.append (Z)Ljava/lang/StringBuffer;
    GOTO L16
   L17
   FRAME FULL [] [java/lang/Throwable]
    NOP
    NOP
    NOP
    NOP
    NOP
    ATHROW
   L16
   FRAME FULL [net/sf/cglib/proxy/Enhancer$EnhancerKey$$KeyFactoryByCGLIB$$7fb24d72] [java/lang/StringBuffer]
    LDC ", "
    INVOKEVIRTUAL java/lang/StringBuffer.append (Ljava/lang/String;)Ljava/lang/StringBuffer;
    ALOAD 0
    GETFIELD net/sf/cglib/proxy/Enhancer$EnhancerKey$$KeyFactoryByCGLIB$$7fb24d72.FIELD_5 : Z
    INVOKEVIRTUAL java/lang/StringBuffer.append (Z)Ljava/lang/StringBuffer;
    GOTO L18
   L19
   FRAME FULL [] [java/lang/Throwable]
    NOP
    NOP
    NOP
    NOP
    NOP
    ATHROW
   L18
   FRAME FULL [net/sf/cglib/proxy/Enhancer$EnhancerKey$$KeyFactoryByCGLIB$$7fb24d72] [java/lang/StringBuffer]
    LDC ", "
    INVOKEVIRTUAL java/lang/StringBuffer.append (Ljava/lang/String;)Ljava/lang/StringBuffer;
    ALOAD 0
    GETFIELD net/sf/cglib/proxy/Enhancer$EnhancerKey$$KeyFactoryByCGLIB$$7fb24d72.FIELD_6 : Ljava/lang/Long;
    DUP
    IFNULL L20
    INVOKEVIRTUAL java/lang/Object.toString ()Ljava/lang/String;
    INVOKEVIRTUAL java/lang/StringBuffer.append (Ljava/lang/String;)Ljava/lang/StringBuffer;
    GOTO L21
   L20
   FRAME FULL [net/sf/cglib/proxy/Enhancer$EnhancerKey$$KeyFactoryByCGLIB$$7fb24d72] [java/lang/StringBuffer java/lang/Long]
    POP
    LDC "null"
    INVOKEVIRTUAL java/lang/StringBuffer.append (Ljava/lang/String;)Ljava/lang/StringBuffer;
   L21
   FRAME FULL [net/sf/cglib/proxy/Enhancer$EnhancerKey$$KeyFactoryByCGLIB$$7fb24d72] [java/lang/StringBuffer]
    INVOKEVIRTUAL java/lang/StringBuffer.toString ()Ljava/lang/String;
    ARETURN
    MAXSTACK = 4
    MAXLOCALS = 5
}
