// class version 46.0 (46)
// access flags 0x1
public class net/sf/cglib/core/MethodWrapper$MethodWrapperKey$$KeyFactoryByCGLIB$$d45e49f7 extends net/sf/cglib/core/KeyFactory  implements net/sf/cglib/core/MethodWrapper$MethodWrapperKey  {

  // compiled from: <generated>

  // access flags 0x12
  private final Ljava/lang/String; FIELD_0

  // access flags 0x12
  private final [Ljava/lang/String; FIELD_1

  // access flags 0x12
  private final Ljava/lang/String; FIELD_2

  // access flags 0x1
  public <init>()V
    ALOAD 0
    INVOKESPECIAL net/sf/cglib/core/KeyFactory.<init> ()V
    RETURN
    MAXSTACK = 1
    MAXLOCALS = 1

  // access flags 0x1
  public newInstance(Ljava/lang/String;[Ljava/lang/String;Ljava/lang/String;)Ljava/lang/Object;
    NEW net/sf/cglib/core/MethodWrapper$MethodWrapperKey$$KeyFactoryByCGLIB$$d45e49f7
    DUP
    ALOAD 1
    ALOAD 2
    ALOAD 3
    INVOKESPECIAL net/sf/cglib/core/MethodWrapper$MethodWrapperKey$$KeyFactoryByCGLIB$$d45e49f7.<init> (Ljava/lang/String;[Ljava/lang/String;Ljava/lang/String;)V
    ARETURN
    MAXSTACK = 5
    MAXLOCALS = 4

  // access flags 0x1
  public <init>(Ljava/lang/String;[Ljava/lang/String;Ljava/lang/String;)V
    ALOAD 0
    INVOKESPECIAL net/sf/cglib/core/KeyFactory.<init> ()V
    ALOAD 0
    DUP
    ALOAD 1
    PUTFIELD net/sf/cglib/core/MethodWrapper$MethodWrapperKey$$KeyFactoryByCGLIB$$d45e49f7.FIELD_0 : Ljava/lang/String;
    DUP
    ALOAD 2
    PUTFIELD net/sf/cglib/core/MethodWrapper$MethodWrapperKey$$KeyFactoryByCGLIB$$d45e49f7.FIELD_1 : [Ljava/lang/String;
    DUP
    ALOAD 3
    PUTFIELD net/sf/cglib/core/MethodWrapper$MethodWrapperKey$$KeyFactoryByCGLIB$$d45e49f7.FIELD_2 : Ljava/lang/String;
    RETURN
    MAXSTACK = 3
    MAXLOCALS = 4

  // access flags 0x1
  public hashCode()I
    LDC 938313161
    ALOAD 0
    GETFIELD net/sf/cglib/core/MethodWrapper$MethodWrapperKey$$KeyFactoryByCGLIB$$d45e49f7.FIELD_0 : Ljava/lang/String;
    SWAP
    LDC 362693231
    IMUL
    SWAP
    DUP
    IFNULL L0
    INVOKEVIRTUAL java/lang/Object.hashCode ()I
    GOTO L1
   L0
   FRAME FULL [net/sf/cglib/core/MethodWrapper$MethodWrapperKey$$KeyFactoryByCGLIB$$d45e49f7] [I java/lang/String]
    POP
    ICONST_0
   L1
   FRAME FULL [net/sf/cglib/core/MethodWrapper$MethodWrapperKey$$KeyFactoryByCGLIB$$d45e49f7] [I I]
    IADD
    ALOAD 0
    GETFIELD net/sf/cglib/core/MethodWrapper$MethodWrapperKey$$KeyFactoryByCGLIB$$d45e49f7.FIELD_1 : [Ljava/lang/String;
    DUP
    IFNULL L2
    ASTORE 1
    ICONST_0
    ISTORE 2
    GOTO L3
   L4
   FRAME FULL [net/sf/cglib/core/MethodWrapper$MethodWrapperKey$$KeyFactoryByCGLIB$$d45e49f7 [Ljava/lang/String; I] [I]
    ALOAD 1
    ILOAD 2
    AALOAD
    SWAP
    LDC 362693231
    IMUL
    SWAP
    DUP
    IFNULL L5
    INVOKEVIRTUAL java/lang/Object.hashCode ()I
    GOTO L6
   L5
   FRAME FULL [net/sf/cglib/core/MethodWrapper$MethodWrapperKey$$KeyFactoryByCGLIB$$d45e49f7 [Ljava/lang/String; I] [I java/lang/String]
    POP
    ICONST_0
   L6
   FRAME FULL [net/sf/cglib/core/MethodWrapper$MethodWrapperKey$$KeyFactoryByCGLIB$$d45e49f7 [Ljava/lang/String; I] [I I]
    IADD
    IINC 2 1
   L3
   FRAME FULL [net/sf/cglib/core/MethodWrapper$MethodWrapperKey$$KeyFactoryByCGLIB$$d45e49f7 [Ljava/lang/String; I] [I]
    ILOAD 2
    ALOAD 1
    ARRAYLENGTH
    IF_ICMPLT L4
    GOTO L7
   L2
   FRAME FULL [net/sf/cglib/core/MethodWrapper$MethodWrapperKey$$KeyFactoryByCGLIB$$d45e49f7] [I [Ljava/lang/String;]
    POP
   L7
   FRAME FULL [net/sf/cglib/core/MethodWrapper$MethodWrapperKey$$KeyFactoryByCGLIB$$d45e49f7] [I]
    ALOAD 0
    GETFIELD net/sf/cglib/core/MethodWrapper$MethodWrapperKey$$KeyFactoryByCGLIB$$d45e49f7.FIELD_2 : Ljava/lang/String;
    SWAP
    LDC 362693231
    IMUL
    SWAP
    DUP
    IFNULL L8
    INVOKEVIRTUAL java/lang/Object.hashCode ()I
    GOTO L9
   L8
   FRAME FULL [net/sf/cglib/core/MethodWrapper$MethodWrapperKey$$KeyFactoryByCGLIB$$d45e49f7] [I java/lang/String]
    POP
    ICONST_0
   L9
   FRAME FULL [net/sf/cglib/core/MethodWrapper$MethodWrapperKey$$KeyFactoryByCGLIB$$d45e49f7] [I I]
    IADD
    IRETURN
    MAXSTACK = 3
    MAXLOCALS = 3

  // access flags 0x1
  public equals(Ljava/lang/Object;)Z
    ALOAD 1
    INSTANCEOF net/sf/cglib/core/MethodWrapper$MethodWrapperKey$$KeyFactoryByCGLIB$$d45e49f7
    IFEQ L0
    ALOAD 0
    GETFIELD net/sf/cglib/core/MethodWrapper$MethodWrapperKey$$KeyFactoryByCGLIB$$d45e49f7.FIELD_0 : Ljava/lang/String;
    ALOAD 1
    CHECKCAST net/sf/cglib/core/MethodWrapper$MethodWrapperKey$$KeyFactoryByCGLIB$$d45e49f7
    GETFIELD net/sf/cglib/core/MethodWrapper$MethodWrapperKey$$KeyFactoryByCGLIB$$d45e49f7.FIELD_0 : Ljava/lang/String;
    DUP2
    IFNONNULL L1
    IFNONNULL L2
    POP2
    GOTO L3
   L1
   FRAME FULL [net/sf/cglib/core/MethodWrapper$MethodWrapperKey$$KeyFactoryByCGLIB$$d45e49f7 java/lang/Object] [java/lang/String java/lang/String java/lang/String]
    IFNULL L2
    GOTO L4
   L2
   FRAME FULL [net/sf/cglib/core/MethodWrapper$MethodWrapperKey$$KeyFactoryByCGLIB$$d45e49f7 java/lang/Object] [java/lang/String java/lang/String]
    POP2
    GOTO L0
   L4
   FRAME FULL [net/sf/cglib/core/MethodWrapper$MethodWrapperKey$$KeyFactoryByCGLIB$$d45e49f7 java/lang/Object] [java/lang/String java/lang/String]
    INVOKEVIRTUAL java/lang/Object.equals (Ljava/lang/Object;)Z
    IFEQ L0
   L3
   FRAME FULL [net/sf/cglib/core/MethodWrapper$MethodWrapperKey$$KeyFactoryByCGLIB$$d45e49f7 java/lang/Object] []
    ALOAD 0
    GETFIELD net/sf/cglib/core/MethodWrapper$MethodWrapperKey$$KeyFactoryByCGLIB$$d45e49f7.FIELD_1 : [Ljava/lang/String;
    ALOAD 1
    CHECKCAST net/sf/cglib/core/MethodWrapper$MethodWrapperKey$$KeyFactoryByCGLIB$$d45e49f7
    GETFIELD net/sf/cglib/core/MethodWrapper$MethodWrapperKey$$KeyFactoryByCGLIB$$d45e49f7.FIELD_1 : [Ljava/lang/String;
    DUP2
    IFNONNULL L5
    IFNONNULL L6
    POP2
    GOTO L7
   L5
   FRAME FULL [net/sf/cglib/core/MethodWrapper$MethodWrapperKey$$KeyFactoryByCGLIB$$d45e49f7 java/lang/Object] [[Ljava/lang/String; [Ljava/lang/String; [Ljava/lang/String;]
    IFNULL L6
    GOTO L8
   L6
   FRAME FULL [net/sf/cglib/core/MethodWrapper$MethodWrapperKey$$KeyFactoryByCGLIB$$d45e49f7 java/lang/Object] [[Ljava/lang/String; [Ljava/lang/String;]
    POP2
    GOTO L0
   L8
   FRAME FULL [net/sf/cglib/core/MethodWrapper$MethodWrapperKey$$KeyFactoryByCGLIB$$d45e49f7 java/lang/Object] [[Ljava/lang/String; [Ljava/lang/String;]
    DUP2
    ARRAYLENGTH
    SWAP
    ARRAYLENGTH
    IF_ICMPEQ L9
    POP2
    GOTO L0
   L9
   FRAME FULL [net/sf/cglib/core/MethodWrapper$MethodWrapperKey$$KeyFactoryByCGLIB$$d45e49f7 java/lang/Object] [[Ljava/lang/String; [Ljava/lang/String;]
    ASTORE 2
    ASTORE 3
    ICONST_0
    ISTORE 4
    GOTO L10
   L11
   FRAME FULL [net/sf/cglib/core/MethodWrapper$MethodWrapperKey$$KeyFactoryByCGLIB$$d45e49f7 java/lang/Object [Ljava/lang/String; [Ljava/lang/String; I] []
    ALOAD 2
    ILOAD 4
    AALOAD
    ALOAD 3
    ILOAD 4
    AALOAD
    DUP2
    IFNONNULL L12
    IFNONNULL L13
    POP2
    GOTO L14
   L12
   FRAME FULL [net/sf/cglib/core/MethodWrapper$MethodWrapperKey$$KeyFactoryByCGLIB$$d45e49f7 java/lang/Object [Ljava/lang/String; [Ljava/lang/String; I] [java/lang/String java/lang/String java/lang/String]
    IFNULL L13
    GOTO L15
   L13
   FRAME FULL [net/sf/cglib/core/MethodWrapper$MethodWrapperKey$$KeyFactoryByCGLIB$$d45e49f7 java/lang/Object [Ljava/lang/String; [Ljava/lang/String; I] [java/lang/String java/lang/String]
    POP2
    GOTO L0
   L15
   FRAME FULL [net/sf/cglib/core/MethodWrapper$MethodWrapperKey$$KeyFactoryByCGLIB$$d45e49f7 java/lang/Object [Ljava/lang/String; [Ljava/lang/String; I] [java/lang/String java/lang/String]
    INVOKEVIRTUAL java/lang/Object.equals (Ljava/lang/Object;)Z
    IFEQ L0
   L14
   FRAME FULL [net/sf/cglib/core/MethodWrapper$MethodWrapperKey$$KeyFactoryByCGLIB$$d45e49f7 java/lang/Object [Ljava/lang/String; [Ljava/lang/String; I] []
    IINC 4 1
   L10
   FRAME FULL [net/sf/cglib/core/MethodWrapper$MethodWrapperKey$$KeyFactoryByCGLIB$$d45e49f7 java/lang/Object [Ljava/lang/String; [Ljava/lang/String; I] []
    ILOAD 4
    ALOAD 2
    ARRAYLENGTH
    IF_ICMPLT L11
   L7
   FRAME FULL [net/sf/cglib/core/MethodWrapper$MethodWrapperKey$$KeyFactoryByCGLIB$$d45e49f7 java/lang/Object] []
    ALOAD 0
    GETFIELD net/sf/cglib/core/MethodWrapper$MethodWrapperKey$$KeyFactoryByCGLIB$$d45e49f7.FIELD_2 : Ljava/lang/String;
    ALOAD 1
    CHECKCAST net/sf/cglib/core/MethodWrapper$MethodWrapperKey$$KeyFactoryByCGLIB$$d45e49f7
    GETFIELD net/sf/cglib/core/MethodWrapper$MethodWrapperKey$$KeyFactoryByCGLIB$$d45e49f7.FIELD_2 : Ljava/lang/String;
    DUP2
    IFNONNULL L16
    IFNONNULL L17
    POP2
    GOTO L18
   L16
   FRAME FULL [net/sf/cglib/core/MethodWrapper$MethodWrapperKey$$KeyFactoryByCGLIB$$d45e49f7 java/lang/Object] [java/lang/String java/lang/String java/lang/String]
    IFNULL L17
    GOTO L19
   L17
   FRAME FULL [net/sf/cglib/core/MethodWrapper$MethodWrapperKey$$KeyFactoryByCGLIB$$d45e49f7 java/lang/Object] [java/lang/String java/lang/String]
    POP2
    GOTO L0
   L19
   FRAME FULL [net/sf/cglib/core/MethodWrapper$MethodWrapperKey$$KeyFactoryByCGLIB$$d45e49f7 java/lang/Object] [java/lang/String java/lang/String]
    INVOKEVIRTUAL java/lang/Object.equals (Ljava/lang/Object;)Z
    IFEQ L0
   L18
   FRAME FULL [net/sf/cglib/core/MethodWrapper$MethodWrapperKey$$KeyFactoryByCGLIB$$d45e49f7 java/lang/Object] []
    ICONST_1
    IRETURN
   L0
   FRAME FULL [net/sf/cglib/core/MethodWrapper$MethodWrapperKey$$KeyFactoryByCGLIB$$d45e49f7 java/lang/Object] []
    ICONST_0
    IRETURN
    MAXSTACK = 4
    MAXLOCALS = 5

  // access flags 0x1
  public toString()Ljava/lang/String;
    NEW java/lang/StringBuffer
    DUP
    INVOKESPECIAL java/lang/StringBuffer.<init> ()V
    ALOAD 0
    GETFIELD net/sf/cglib/core/MethodWrapper$MethodWrapperKey$$KeyFactoryByCGLIB$$d45e49f7.FIELD_0 : Ljava/lang/String;
    DUP
    IFNULL L0
    INVOKEVIRTUAL java/lang/Object.toString ()Ljava/lang/String;
    INVOKEVIRTUAL java/lang/StringBuffer.append (Ljava/lang/String;)Ljava/lang/StringBuffer;
    GOTO L1
   L0
   FRAME FULL [net/sf/cglib/core/MethodWrapper$MethodWrapperKey$$KeyFactoryByCGLIB$$d45e49f7] [java/lang/StringBuffer java/lang/String]
    POP
    LDC "null"
    INVOKEVIRTUAL java/lang/StringBuffer.append (Ljava/lang/String;)Ljava/lang/StringBuffer;
   L1
   FRAME FULL [net/sf/cglib/core/MethodWrapper$MethodWrapperKey$$KeyFactoryByCGLIB$$d45e49f7] [java/lang/StringBuffer]
    LDC ", "
    INVOKEVIRTUAL java/lang/StringBuffer.append (Ljava/lang/String;)Ljava/lang/StringBuffer;
    ALOAD 0
    GETFIELD net/sf/cglib/core/MethodWrapper$MethodWrapperKey$$KeyFactoryByCGLIB$$d45e49f7.FIELD_1 : [Ljava/lang/String;
    DUP
    IFNULL L2
    SWAP
    LDC "{"
    INVOKEVIRTUAL java/lang/StringBuffer.append (Ljava/lang/String;)Ljava/lang/StringBuffer;
    SWAP
    ASTORE 1
    ICONST_0
    ISTORE 2
    GOTO L3
   L4
   FRAME FULL [net/sf/cglib/core/MethodWrapper$MethodWrapperKey$$KeyFactoryByCGLIB$$d45e49f7 [Ljava/lang/String; I] [java/lang/StringBuffer]
    ALOAD 1
    ILOAD 2
    AALOAD
    DUP
    IFNULL L5
    INVOKEVIRTUAL java/lang/Object.toString ()Ljava/lang/String;
    INVOKEVIRTUAL java/lang/StringBuffer.append (Ljava/lang/String;)Ljava/lang/StringBuffer;
    GOTO L6
   L5
   FRAME FULL [net/sf/cglib/core/MethodWrapper$MethodWrapperKey$$KeyFactoryByCGLIB$$d45e49f7 [Ljava/lang/String; I] [java/lang/StringBuffer java/lang/String]
    POP
    LDC "null"
    INVOKEVIRTUAL java/lang/StringBuffer.append (Ljava/lang/String;)Ljava/lang/StringBuffer;
   L6
   FRAME FULL [net/sf/cglib/core/MethodWrapper$MethodWrapperKey$$KeyFactoryByCGLIB$$d45e49f7 [Ljava/lang/String; I] [java/lang/StringBuffer]
    LDC ", "
    INVOKEVIRTUAL java/lang/StringBuffer.append (Ljava/lang/String;)Ljava/lang/StringBuffer;
    IINC 2 1
   L3
   FRAME FULL [net/sf/cglib/core/MethodWrapper$MethodWrapperKey$$KeyFactoryByCGLIB$$d45e49f7 [Ljava/lang/String; I] [java/lang/StringBuffer]
    ILOAD 2
    ALOAD 1
    ARRAYLENGTH
    IF_ICMPLT L4
    DUP
    DUP
    INVOKEVIRTUAL java/lang/StringBuffer.length ()I
    ICONST_2
    ISUB
    INVOKEVIRTUAL java/lang/StringBuffer.setLength (I)V
    LDC "}"
    INVOKEVIRTUAL java/lang/StringBuffer.append (Ljava/lang/String;)Ljava/lang/StringBuffer;
    GOTO L7
   L2
   FRAME FULL [net/sf/cglib/core/MethodWrapper$MethodWrapperKey$$KeyFactoryByCGLIB$$d45e49f7] [java/lang/StringBuffer [Ljava/lang/String;]
    POP
    LDC "null"
    INVOKEVIRTUAL java/lang/StringBuffer.append (Ljava/lang/String;)Ljava/lang/StringBuffer;
   L7
   FRAME FULL [net/sf/cglib/core/MethodWrapper$MethodWrapperKey$$KeyFactoryByCGLIB$$d45e49f7] [java/lang/StringBuffer]
    LDC ", "
    INVOKEVIRTUAL java/lang/StringBuffer.append (Ljava/lang/String;)Ljava/lang/StringBuffer;
    ALOAD 0
    GETFIELD net/sf/cglib/core/MethodWrapper$MethodWrapperKey$$KeyFactoryByCGLIB$$d45e49f7.FIELD_2 : Ljava/lang/String;
    DUP
    IFNULL L8
    INVOKEVIRTUAL java/lang/Object.toString ()Ljava/lang/String;
    INVOKEVIRTUAL java/lang/StringBuffer.append (Ljava/lang/String;)Ljava/lang/StringBuffer;
    GOTO L9
   L8
   FRAME FULL [net/sf/cglib/core/MethodWrapper$MethodWrapperKey$$KeyFactoryByCGLIB$$d45e49f7] [java/lang/StringBuffer java/lang/String]
    POP
    LDC "null"
    INVOKEVIRTUAL java/lang/StringBuffer.append (Ljava/lang/String;)Ljava/lang/StringBuffer;
   L9
   FRAME FULL [net/sf/cglib/core/MethodWrapper$MethodWrapperKey$$KeyFactoryByCGLIB$$d45e49f7] [java/lang/StringBuffer]
    INVOKEVIRTUAL java/lang/StringBuffer.toString ()Ljava/lang/String;
    ARETURN
    MAXSTACK = 4
    MAXLOCALS = 3
}
